caseflow-0.1.4.dist-info/METADATA
caseflow-0.1.4.dist-info/WHEEL
caseflow-0.1.4.dist-info/entry_points.txt
caseflow/__init__.py
caseflow/__main__.py
caseflow/callbacks/__init__.py
caseflow/callbacks/base.py
caseflow/callbacks/stdout.py
caseflow/case_step.py
caseflow/debug_case_step.py
caseflow/jsonschema.py
caseflow/main.py
caseflow/mime.types.allow.ini
caseflow/mime.types.forbid.ini
caseflow/model.py
caseflow/run_case.py
caseflow/utils/__init__.py
caseflow/utils/concurrency.py
caseflow/utils/parameterization.py
caseflow-0.1.4.dist-info/RECORD
