Metadata-Version: 2.1
Name: caseflow
Version: 0.1.4
Summary: Replay the interface recording packets, orchestrate and run them based on the LCEL using the langChain.
Keywords: caseflow,langchain,LCEL,RPA,case,interface test
Author-Email: gnakw <gnakw@outlook.com>
License: MIT
Requires-Python: >=3.11
Requires-Dist: haralyzer>=2.4.0
Requires-Dist: aiohttp>=3.9.5
Requires-Dist: jsonpath>=0.82.2
Requires-Dist: pytest>=8.1.1
Requires-Dist: pytest-html>=4.1.1
Requires-Dist: pytest-asyncio>=0.23.6
Requires-Dist: jsonschema>=4.21.1
Requires-Dist: langchain-core>=0.1.45
Requires-Dist: langchain>=0.1.16
Requires-Dist: langchain-openai>=0.1.3
Requires-Dist: langchainhub>=0.1.15
Requires-Dist: beautifulsoup4>=4.12.3
Requires-Dist: lxml>=5.2.2
